k3cat/__init__.py
k3cat/cat.py
k3cat/synopsis.py
k3cat-0.1.3.dist-info/licenses/LICENSE
k3cat-0.1.3.dist-info/METADATA
k3cat-0.1.3.dist-info/WHEEL
k3cat-0.1.3.dist-info/top_level.txt
k3cat-0.1.3.dist-info/RECORD
